{
  "name": "temp/XdyoEqwuRshZvP5BtjzqhQHmtDWS/1756847081103_phone-1.svg",
  "bucket": "verona-ffbcd.firebasestorage.app",
  "metageneration": 1,
  "generation": 1756847081114,
  "contentType": "image/svg+xml",
  "storageClass": "STANDARD",
  "contentDisposition": "inline",
  "downloadTokens": [
    "6644f593-8539-479a-91ef-906e42ab1f3e"
  ],
  "etag": "KvkYNUy0wtbrPf5yyVuAZp5aHy8",
  "customMetadata": {},
  "timeCreated": "2025-09-02T21:04:41.114Z",
  "updated": "2025-09-02T21:04:41.114Z",
  "size": 7000,
  "md5Hash": "iQPIJuesJUYcY+Bjoqv0xA==",
  "crc32c": "52025617"
}